{
  "$type": "Assets.Code.Editor.Helpers.SimpleCardDataExporter+SimpleData, Assembly-CSharp-Editor",
  "Id": 454,
  "Name": "maskemane_niveau_3",
  "CardType": 0,
  "CostAP": 7,
  "Life": 4,
  "Attack": 4,
  "MovementPoint": 3,
  "Families": [
    45
  ],
  "IsToken": false,
  "Rarity": 4,
  "GodType": 0,
  "Extension": 1,
  "LinkedCards": [],
  "Texts": {
    "$type": "Assets.Code.Editor.Helpers.SimpleCardDataExporter+TextData, Assembly-CSharp-Editor",
    "NameFR": "Maskemane Psycho",
    "DescFR": "<b>APPARITION :</b>\nDéfausse votre main et celle de votre adversaire puis chaque joueur pioche 5 cartes.",
    "NameEN": "Psychopath Maskemane",
    "DescEN": "<b>APPEARANCC:</b>\nDiscard your hand as well as the opponent's and then both players draw 5 cards.",
    "NameES": "Maskeman - Sáikopat",
    "DescES": "<b>APARICIÓN:</b>\nDescarta tu mano y la de tu contrincante, y cada jugador roba 5 cartas."
  }
}