{
  "$type": "Assets.Code.Editor.Helpers.SimpleCardDataExporter+SimpleData, Assembly-CSharp-Editor",
  "Id": 153,
  "Name": "miranda",
  "CardType": 0,
  "CostAP": 5,
  "Life": 2,
  "Attack": 2,
  "MovementPoint": 3,
  "Families": [
    8
  ],
  "IsToken": false,
  "Rarity": 3,
  "GodType": 0,
  "Extension": 1,
  "LinkedCards": [],
  "Texts": {
    "$type": "Assets.Code.Editor.Helpers.SimpleCardDataExporter+TextData, Assembly-CSharp-Editor",
    "NameFR": "Miranda",
    "DescFR": "<b>APPARITION :</b>\nPrend le contrôle des invocations adverses autour d'elle jusqu'à sa mort.",
    "NameEN": "Miranda",
    "DescEN": "<b>APPEARANCE:</b>\nTakes control of enemy Summons on adjacent cells until her death.",
    "NameES": "Miranda",
    "DescES": "<b>APARICIÓN: </b>\nToma el control de las invocaciones enemigas que estén a su alrededor hasta su muerte."
  }
}